usherai/__init__.py
usherai/core_module.py
usherai_001-0.0.1.dist-info/METADATA
usherai_001-0.0.1.dist-info/WHEEL
usherai_001-0.0.1.dist-info/top_level.txt
usherai_001-0.0.1.dist-info/RECORD
