Metadata-Version: 2.1
Name: usherai-001
Version: 0.0.1
Summary: Experimental A.I. Intergration Module, including text to speech
Author: Bertran Usher
Author-email: <bjusher820@gmail.com>
Keywords: python,openai,ai,artificial intelligence
Classifier: Development Status :: 1 - Planning
Classifier: Intended Audience :: Developers
Classifier: Programming Language :: Python :: 3
Classifier: Operating System :: Unix
Classifier: Operating System :: MacOS :: MacOS X
Classifier: Operating System :: Microsoft :: Windows
Requires-Dist: openai
Requires-Dist: pyttsx3
